mov_cli_ms/__init__.py
mov_cli_ms/jellyfin/scraper.py
mov_cli_ms/plex/scraper.py
mov_cli_ms-1.0.0.dist-info/LICENSE
mov_cli_ms-1.0.0.dist-info/METADATA
mov_cli_ms-1.0.0.dist-info/WHEEL
mov_cli_ms-1.0.0.dist-info/top_level.txt
mov_cli_ms-1.0.0.dist-info/RECORD
