Metadata-Version: 2.1
Name: mov-cli-ms
Version: 1.0.0
Summary: A mov-cli v4 plugin for watching whatever you desire. 🌟
Author-email: Ananas <ananas@r3tr0ananas.pro>
License: MIT License
Project-URL: GitHub, https://github.com/mov-cli/mov-cli-media-server
Project-URL: BugTracker, https://github.com/mov-cli/mov-cli-media-server/issues
Keywords: mov-cli,amazing plugin
Classifier: Operating System :: Microsoft :: Windows :: Windows 11
Classifier: Operating System :: Microsoft :: Windows :: Windows 10
Classifier: Operating System :: POSIX :: Linux
Classifier: License :: OSI Approved :: MIT License
Classifier: Programming Language :: Python :: 3.8
Classifier: Programming Language :: Python :: 3.9
Classifier: Programming Language :: Python :: 3.10
Classifier: Programming Language :: Python :: 3.11
Classifier: Programming Language :: Python :: 3.12
Requires-Python: >=3.8
License-File: LICENSE
Requires-Dist: requests
Requires-Dist: mov-cli >=4.3
Requires-Dist: importlib-metadata ; python_version < "3.8"
Provides-Extra: dev
Requires-Dist: ruff ; extra == 'dev'
Requires-Dist: build ; extra == 'dev'
